LICENSE
MANIFEST.in
README.rst
setup.cfg
setup.py
src/cpcli/__init__.py
src/cpcli/cmdline.py
src/cpcli/question.py
src/cpcli/runner.py
src/cpcli/testcase.py
src/cpcli.egg-info/PKG-INFO
src/cpcli.egg-info/SOURCES.txt
src/cpcli.egg-info/dependency_links.txt
src/cpcli.egg-info/entry_points.txt
src/cpcli.egg-info/not-zip-safe
src/cpcli.egg-info/requires.txt
src/cpcli.egg-info/top_level.txt
src/cpcli/commands/__init__.py
src/cpcli/commands/download.py
src/cpcli/commands/init.py
src/cpcli/commands/run.py
src/cpcli/commands/show.py
src/cpcli/commands/testcase.py
src/cpcli/platforms/__init__.py
src/cpcli/platforms/atcoder.py
src/cpcli/platforms/codechef.py
src/cpcli/platforms/codeforces.py
src/cpcli/platforms/cses.py
src/cpcli/templates/Template.cpp
src/cpcli/templates/__init__.py
src/cpcli/utils/__init__.py
src/cpcli/utils/__main__.py
src/cpcli/utils/cmdtypes.py
src/cpcli/utils/config.py
src/cpcli/utils/constants.py
src/cpcli/utils/exceptions.py
src/cpcli/utils/log.py
src/cpcli/utils/misc.py
src/cpcli/utils/python.py
src/cpcli/utils/uri.py