Metadata-Version: 2.1
Name: cpcli
Version: 0.8
Summary: Competitive Programming CLI
Home-page: https://github.com/adityaa30/cpcli
Author: Aditya Kumar
Author-email: k.aditya00@gmail.com
License: MIT License
Download-URL: https://github.com/adityaa30/cpcli/releases/tag/0.8
Keywords: CLI,Competitive Programming
Platform: UNKNOWN
Classifier: Topic :: Education
Classifier: License :: OSI Approved :: MIT License
Classifier: Programming Language :: Python :: 3
Classifier: Programming Language :: Python :: 3.6
Classifier: Programming Language :: Python :: 3.7
Classifier: Programming Language :: Python :: 3.8
Requires-Python: >=3.6
License-File: LICENSE
